{
	"configurations" : 
	[
		{
			"directories" : 
			[
				{
					"build" : ".",
					"jsonFile" : "directory-.-Debug-d0094a50bb2071803777.json",
					"minimumCMakeVersion" : 
					{
						"string" : "3.20"
					},
					"projectIndex" : 0,
					"source" : ".",
					"targetIndexes" : 
					[
						0,
						1
					]
				}
			],
			"name" : "Debug",
			"projects" : 
			[
				{
					"directoryIndexes" : 
					[
						0
					],
					"name" : "Music_Box2",
					"targetIndexes" : 
					[
						0,
						1
					]
				}
			],
			"targets" : 
			[
				{
					"directoryIndex" : 0,
					"id" : "Music_Box2::@6890427a1f51a3e7e1df",
					"jsonFile" : "target-Music_Box2-Debug-1e77ce56fa8fb7712be1.json",
					"name" : "Music_Box2",
					"projectIndex" : 0
				},
				{
					"directoryIndex" : 0,
					"id" : "Music_Box2_Test::@6890427a1f51a3e7e1df",
					"jsonFile" : "target-Music_Box2_Test-Debug-9752607884bb5e4ec43c.json",
					"name" : "Music_Box2_Test",
					"projectIndex" : 0
				}
			]
		}
	],
	"kind" : "codemodel",
	"paths" : 
	{
		"build" : "C:/Users/kalka/Documents/Music_box2/build",
		"source" : "C:/Users/kalka/Documents/Music_box2"
	},
	"version" : 
	{
		"major" : 2,
		"minor" : 6
	}
}
